RTL/ALU_control.v
module alu_control (
    input  [6:0] opcode,
    input  [2:0] funct3,
    input  [6:0] funct7,   
    output reg [3:0] alu_ctrl
);

always @(*) begin
    alu_ctrl = 4'b0000; 
    case (opcode)
        // R-TYPE (Register)
        7'b0110011: begin
            case (funct3)

                3'b000: begin
                    if (funct7 == 7'b0100000)
                        alu_ctrl = 4'b0001; // SUB
                    else
                        alu_ctrl = 4'b0000; // ADD
                end

                3'b111: alu_ctrl = 4'b0010; // AND
                3'b110: alu_ctrl = 4'b0011; // OR
                3'b100: alu_ctrl = 4'b0100; // XOR
                3'b001: alu_ctrl = 4'b0101; // SLL

                3'b101: begin
                    if (funct7 == 7'b0100000)
                        alu_ctrl = 4'b0111; // SRA
                    else 
                        alu_ctrl = 4'b0110; // SRL
                end

                3'b010: alu_ctrl = 4'b1000; // SLT
                3'b011: alu_ctrl = 4'b1001; // SLTU

            endcase
        end

        // I-TYPE (Immediate ALU)
        7'b0010011: begin
            case (funct3)

                3'b000: alu_ctrl = 4'b0000; // ADDI
                3'b111: alu_ctrl = 4'b0010; // ANDI
                3'b110: alu_ctrl = 4'b0011; // ORI
                3'b100: alu_ctrl = 4'b0100; // XORI
                3'b010: alu_ctrl = 4'b1000; // SLTI
                3'b011: alu_ctrl = 4'b1001; // SLTIU
                3'b001: alu_ctrl = 4'b0101; // SLLI

                // SRLI / SRAI (funct7 = instr[31:25])
                3'b101: begin
                    if (funct7 == 7'b0100000)
                        alu_ctrl = 4'b0111; // SRAI
                    else
                        alu_ctrl = 4'b0110; // SRLI
                end

            endcase
        end

        // LOAD / STORE (Address Calc)
        7'b0000011: alu_ctrl = 4'b0000; // LOAD -> ADD
        7'b0100011: alu_ctrl = 4'b0000; // STORE -> ADD

        // BRANCH (Comparison)
        7'b1100011: begin
            case (funct3)
                3'b000: alu_ctrl = 4'b0001; // BEQ -> SUB
                3'b001: alu_ctrl = 4'b0001; // BNE -> SUB
                3'b100: alu_ctrl = 4'b1000; // BLT
                3'b101: alu_ctrl = 4'b1000; // BGE
                3'b110: alu_ctrl = 4'b1001; // BLTU
                3'b111: alu_ctrl = 4'b1001; // BGEU
            endcase
        end

        // U-TYPE
        7'b0110111: alu_ctrl = 4'b1010; // LUI -> PASS B
        7'b0010111: alu_ctrl = 4'b0000; // AUIPC -> ADD (PC + imm)

        // JUMP
        7'b1101111: alu_ctrl = 4'b0000; // JAL -> ADD
        7'b1100111: alu_ctrl = 4'b0000; // JALR -> ADD

    endcase
end

endmodule

Testbenches/ALU_control_tb.v
`timescale 1ns/1ps

module alu_control_tb;
    reg  [6:0] opcode;
    reg  [2:0] funct3;
    reg  [6:0] funct7;
    wire [3:0] alu_ctrl;

    alu_control uut (
        .opcode(opcode),
        .funct3(funct3),
        .funct7(funct7),
        .alu_ctrl(alu_ctrl)
    );
    initial begin
        $dumpfile("alu_control_tb.vcd");
        $dumpvars(0, alu_control_tb);
        $monitor("t=%0t | opcode=%b funct3=%b funct7=%b | alu_ctrl=%b",
                 $time, opcode, funct3, funct7, alu_ctrl);
        opcode = 7'b0; funct3 = 3'b0; funct7 = 7'b0;
        // R-type ADD
        #10 opcode = 7'b0110011; funct3 = 3'b000; funct7 = 7'b0000000;
        // R-type SUB
        #10 opcode = 7'b0110011; funct3 = 3'b000; funct7 = 7'b0100000;
        // R-type AND
        #10 opcode = 7'b0110011; funct3 = 3'b111; funct7 = 7'b0000000;
        // R-type OR
        #10 opcode = 7'b0110011; funct3 = 3'b110; funct7 = 7'b0000000;
        // R-type XOR
        #10 opcode = 7'b0110011; funct3 = 3'b100; funct7 = 7'b0000000;
        // R-type SLL
        #10 opcode = 7'b0110011; funct3 = 3'b001; funct7 = 7'b0000000;
        // R-type SRL
        #10 opcode = 7'b0110011; funct3 = 3'b101; funct7 = 7'b0000000;
        // R-type SRA
        #10 opcode = 7'b0110011; funct3 = 3'b101; funct7 = 7'b0100000;
        // I-type ADDI
        #10 opcode = 7'b0010011; funct3 = 3'b000; funct7 = 7'b0000000;
        // I-type SRAI
        #10 opcode = 7'b0010011; funct3 = 3'b101; funct7 = 7'b0100000;
        // LOAD
        #10 opcode = 7'b0000011; funct3 = 3'b010; funct7 = 7'b0000000;
        // STORE
        #10 opcode = 7'b0100011; funct3 = 3'b010; funct7 = 7'b0000000;
        // BRANCH BEQ
        #10 opcode = 7'b1100011; funct3 = 3'b000; funct7 = 7'b0000000;
        // LUI
        #10 opcode = 7'b0110111; funct3 = 3'b000; funct7 = 7'b0000000;
        // AUIPC
        #10 opcode = 7'b0010111; funct3 = 3'b000; funct7 = 7'b0000000;
        // JAL
        #10 opcode = 7'b1101111; funct3 = 3'b000; funct7 = 7'b0000000;
        // JALR
        #10 opcode = 7'b1100111; funct3 = 3'b000; funct7 = 7'b0000000;
        #20 $finish;
    end
endmodule

alu_control_tb.vcd
$date
	Fri Jun 19 01:40:01 2026
$end
$version
	Icarus Verilog
$end
$timescale
	1ps
$end
$scope module alu_control_tb $end
$var wire 4 ! alu_ctrl [3:0] $end
$var reg 3 " funct3 [2:0] $end
$var reg 7 # funct7 [6:0] $end
$var reg 7 $ opcode [6:0] $end
$scope module uut $end
$var wire 3 % funct3 [2:0] $end
$var wire 7 & funct7 [6:0] $end
$var wire 7 ' opcode [6:0] $end
$var reg 4 ( alu_ctrl [3:0] $end
$upscope $end
$upscope $end
$enddefinitions $end
$comment Show the parameter values. $end
$dumpall
$end
#0
$dumpvars
b0 (
b0 '
b0 &
b0 %
b0 $
b0 #
b0 "
b0 !
$end
#10000
b110011 $
b110011 '
#20000
b1 !
b1 (
b100000 #
b100000 &
#30000
b10 !
b10 (
b0 #
b0 &
b111 "
b111 %
#40000
b11 !
b11 (
b110 "
b110 %
#50000
b100 !
b100 (
b100 "
b100 %
#60000
b101 !
b101 (
b1 "
b1 %
#70000
b110 !
b110 (
b101 "
b101 %
#80000
b111 !
b111 (
b100000 #
b100000 &
#90000
b0 !
b0 (
b0 #
b0 &
b0 "
b0 %
b10011 $
b10011 '
#100000
b111 !
b111 (
b100000 #
b100000 &
b101 "
b101 %
#110000
b0 !
b0 (
b0 #
b0 &
b10 "
b10 %
b11 $
b11 '
#120000
b100011 $
b100011 '
#130000
b1 !
b1 (
b0 "
b0 %
b1100011 $
b1100011 '
#140000
b1010 !
b1010 (
b110111 $
b110111 '
#150000
b0 !
b0 (
b10111 $
b10111 '
#160000
b1101111 $
b1101111 '
#170000
b1100111 $
b1100111 '
